picopipe/__init__.py
picopipe/_version.py
picopipe-1.0.2.dist-info/LICENSE
picopipe-1.0.2.dist-info/METADATA
picopipe-1.0.2.dist-info/WHEEL
picopipe-1.0.2.dist-info/top_level.txt
picopipe-1.0.2.dist-info/RECORD
