Metadata-Version: 2.1
Name: picopipe
Version: 1.0.2
Summary: A small pipeline framework
Home-page: https://github.com/dsblank/picopipe
Author: Douglas Blank
License: Apache 2.0
Keywords: machine learning,artificial intelligence,pipelines,python,data science
Platform: Linux
Platform: Mac OS X
Platform: Windows
Classifier: License :: OSI Approved :: BSD License
Classifier: Programming Language :: Python
Classifier: Programming Language :: Python :: 3
Classifier: Programming Language :: Python :: 3.9
Classifier: Programming Language :: Python :: 3.10
Classifier: Programming Language :: Python :: 3.11
Requires-Python: >=3.9
License-File: LICENSE
Requires-Dist: joblib
